lagrangebench2/__init__.py
lagrangebench2/case_setup/__init__.py
lagrangebench2/case_setup/case.py
lagrangebench2/case_setup/features.py
lagrangebench2/case_setup/partition.py
lagrangebench2/data/__init__.py
lagrangebench2/data/data.py
lagrangebench2/data/utils.py
lagrangebench2/defaults.py
lagrangebench2/evaluate/__init__.py
lagrangebench2/evaluate/metrics.py
lagrangebench2/evaluate/rollout.py
lagrangebench2/models/__init__.py
lagrangebench2/models/base.py
lagrangebench2/models/egnn.py
lagrangebench2/models/gns.py
lagrangebench2/models/linear.py
lagrangebench2/models/painn.py
lagrangebench2/models/segnn.py
lagrangebench2/models/utils.py
lagrangebench2/train/__init__.py
lagrangebench2/train/strats.py
lagrangebench2/train/trainer.py
lagrangebench2/utils.py
lagrangebench2-0.1.15.dist-info/LICENSE
lagrangebench2-0.1.15.dist-info/METADATA
lagrangebench2-0.1.15.dist-info/WHEEL
lagrangebench2-0.1.15.dist-info/RECORD
