Metadata-Version: 2.1
Name: lagrangebench2
Version: 0.1.15
Summary: LagrangeBench: A Lagrangian Fluid Mechanics Benchmarking Suite
License: MIT
Author: Artur Toshev
Author-email: artur.toshev@tum.de
Requires-Python: >=3.9,<3.11
Classifier: License :: OSI Approved :: MIT License
Classifier: Programming Language :: Python :: 3
Classifier: Programming Language :: Python :: 3.9
Classifier: Programming Language :: Python :: 3.10
Requires-Dist: PyYAML (>=6.0)
Requires-Dist: cloudpickle (>=2.2.1)
Requires-Dist: dm-haiku (>=0.0.10)
Requires-Dist: e3nn-jax (==0.20.0)
Requires-Dist: gdown (>=4.7.1,<5.0.0)
Requires-Dist: h5py (>=3.9.0)
Requires-Dist: jax (>=0.4.16,<0.5.0)
Requires-Dist: jax-md (==0.2.8)
Requires-Dist: jmp (>=0.0.4,<0.0.5)
Requires-Dist: jraph (==0.0.6.dev0)
Requires-Dist: matscipy (>=0.8.0,<0.9.0)
Requires-Dist: numpy (>=1.24.4)
Requires-Dist: optax (==0.1.7)
Requires-Dist: ott-jax (>=0.4.4,<0.5.0)
Requires-Dist: pyvista (>=0.42.2)
Requires-Dist: torch (==2.1.0+cpu)
Requires-Dist: wandb (>=0.15.11)
